image_file_converter/__init__.py
image_file_converter/bin.py
image_file_converter/core.py
image_file_converter/utils.py
image_file_converter/version.json
image_file_converter-1.0.1.dist-info/METADATA
image_file_converter-1.0.1.dist-info/WHEEL
image_file_converter-1.0.1.dist-info/entry_points.txt
image_file_converter-1.0.1.dist-info/top_level.txt
image_file_converter-1.0.1.dist-info/RECORD
