Metadata-Version: 2.1
Name: image-file-converter
Version: 1.0.1
Summary: Toolkit for converting image files
Home-page: https://github.com/suqingdong/image_file_converter
Author: suqingdong
Author-email: suqingdong1114@gmail.com
License: MIT License
Platform: UNKNOWN
Classifier: Development Status :: 5 - Production/Stable
Classifier: Operating System :: OS Independent
Classifier: Intended Audience :: Developers
Classifier: License :: OSI Approved :: MIT License
Classifier: Programming Language :: Python
Classifier: Programming Language :: Python :: 3
Classifier: Programming Language :: Python :: 3.10
Classifier: Programming Language :: Python :: 3.11
Classifier: Programming Language :: Python :: 3.12
Classifier: Topic :: Software Development :: Libraries
Requires-Dist: click
Requires-Dist: pillow
Requires-Dist: PyMuPDF
Requires-Dist: reportlab
